Workbook

Sheet Resumo
A1: RESUMO — COMPRAS E EXECUÇÃO (912 NORTE)
A2: Estimativas de mercado (jun/2026). Preencha 'Comprado?' e 'Valor real pago' em cada aba; este resumo soma sozinho.
A4: Prioridade | B4: Total estimado | C4: Total real pago | D4: Itens | E4: Concluídos
A5: 1. Essencial | B5: ='1. Essencial'!H38 | C5: ='1. Essencial'!J38 | D5: =COUNTA('1. Essencial'!A4:A37) | E5: =COUNTIF('1. Essencial'!I4:I37,"Sim")
A6: 2. Alta prioridade | B6: ='2. Alta prioridade'!H9 | C6: ='2. Alta prioridade'!J9 | D6: =COUNTA('2. Alta prioridade'!A4:A8) | E6: =COUNTIF('2. Alta prioridade'!I4:I8,"Sim")
A7: 3. Média prioridade | B7: ='3. Média prioridade'!H8 | C7: ='3. Média prioridade'!J8 | D7: =COUNTA('3. Média prioridade'!A4:A7) | E7: =COUNTIF('3. Média prioridade'!I4:I7,"Sim")
A8: 4. Diferenciação (2ª etapa) | B8: ='4. Diferenciação (2ª etapa)'!H6 | C8: ='4. Diferenciação (2ª etapa)'!J6 | D8: =COUNTA('4. Diferenciação (2ª etapa)'!A4:A5) | E8: =COUNTIF('4. Diferenciação (2ª etapa)'!I4:I5,"Sim")
A9: 5. Pode esperar | B9: ='5. Pode esperar'!H8 | C9: ='5. Pode esperar'!J8 | D9: =COUNTA('5. Pode esperar'!A4:A7) | E9: =COUNTIF('5. Pode esperar'!I4:I7,"Sim")
A10: TOTAL GERAL | B10: =SUM(B5:B9) | C10: =SUM(C5:C9) | D10: =SUM(D5:D9) | E10: =SUM(E5:E9)
A12: Foco imediato: zerar a aba '1. Essencial' (comprado + executado) antes de liberar o anúncio.
A13: Sequência: comprar essencial → executar reforma/montagem → fotos novas → publicar.
A14: PAINEL DE GO-LIVE (nova estratégia)
A15: Estratégia: NÃO comprar tudo antes de abrir. Zerar BLOQUEADORES, abrir com segurança/higiene/foto mínima, gerar caixa e reinvestir por ROI.
A16: Indicador | B16: Valor
A17: Bloqueadores pendentes (Essencial) | B17: =COUNTIFS('1. Essencial'!O4:O37,"Bloqueador",'1. Essencial'!M4:M37,"Pendente*")
A18: Bloqueadores já resolvidos (Essencial) | B18: =COUNTIFS('1. Essencial'!O4:O37,"Bloqueador",'1. Essencial'!M4:M37,"Comprado*")
A19: Pré-go-live desejáveis pendentes (Ess.+Alta) | B19: =COUNTIFS('1. Essencial'!O4:O37,"Pré-go-live",'1. Essencial'!M4:M37,"Pendente*")+COUNTIFS('2. Alta prioridade'!O4:O8,"Pré-go-live",'2. Alta prioridade'!M4:M8,"Pendente*")
A20: Itens adiados (Pós-go-live/Pós-ROI/Não) | B20: =COUNTIF('1. Essencial'!O4:O37,"Pós*")+COUNTIF('1. Essencial'!O4:O37,"Não comprar")+COUNTIF('2. Alta prioridade'!O4:O8,"Pós*")+COUNTIF('2. Alta prioridade'!O4:O8,"Não comprar")
A21: Total já PAGO (todas as abas) | B21: =SUM('1. Essencial'!J4:J37)+SUM('2. Alta prioridade'!J4:J8)+SUM('3. Média prioridade'!J4:J7)+SUM('4. Diferenciação (2ª etapa)'!J4:J5)+SUM('5. Pode esperar'!J4:J7)
A23: Legenda Classe go-live: Bloqueador (não abre sem) · Pré-go-live (desejável antes) · Pós-go-live 30d · Pós-ROI 60d · Não comprar por ora.
A24: Abas 3-5 já são, por natureza, Pós-go-live / Pós-ROI / Não comprar agora.

Sheet 1. Essencial
A1: 1. ESSENCIAL
A2: Tudo que precisa estar comprado E executado ANTES de liberar o anúncio. Amarelo = você preenche.
A3: Item | B3: Tipo | C3: Categoria | D3: Qtd | E3: Especificação mínima | F3: Qualidade | G3: Preço unit. estimado | H3: Total estimado | I3: Sua marcação (Sim/Pretend./Não) | J3: Valor real pago R$ | K3: Link | L3: Observação | M3: Status de execução | N3: Decisão CAPEX | O3: Classe go-live | P3: Data limite | Q3: Responsável | R3: Risco se adiar | S3: Próxima ação
A4: Pintura / retoque de paredes | B4: Serviço | C4: Estrutural | D4: 1 | E4: Branco/neutro; cobrir marcas do inquilino | F4: - | G4: 1500 | H4: =D4*G4 | I4: Pretendido | L4: Maior impacto em foto e limpeza percebida | M4: Pendente (serviço) | N4: Orçar 30/06 | O4: Pré-go-live | P4: 04–08/07 | Q4: Prestador | R4: Fotos/percepção piores | S4: Orçar 30/06; executar na reforma
A5: Faxina pesada + eliminar odor | B5: Serviço | C5: Estrutural | D5: 1 | E5: Pós-obra; arejar imóvel fechado | F5: - | G5: 250 | H5: =D5*G5 | I5: Pretendido | L5: 1ª impressão define a nota | M5: Pendente (serviço) | N5: Contratar | O5: Bloqueador | P5: 09/07 | Q5: Talita/serviço | R5: Imóvel sujo = insalubre / nota baixa | S5: Faxina pesada em 09/07
A6: Reparos funcionais | B6: Serviço | C6: Estrutural | D6: 1 | E6: Chuveiro, descarga, tomadas, vedação do box | F6: - | G6: 400 | H6: =D6*G6 | I6: Pretendido | L6: Conforme vistoria | M6: Pendente (serviço) | N6: Orçar 30/06 | O6: Bloqueador | P6: 04–08/07 | Q6: Prestador | R6: Defeito vira reclamação/dano | S6: Orçar 30/06; reparar
A7: Consertar/alinhar portas de armário | B7: Serviço | C7: Estrutural | D7: 1 | E7: Cozinha (aparecem abertas nas fotos) | F7: - | G7: 250 | H7: =D7*G7 | I7: Pretendido | L7: Tira a cara de abandonado | M7: Pendente (serviço) | N7: Orçar 30/06 | O7: Pré-go-live | P7: 04–08/07 | Q7: Prestador | R7: Cozinha ruim + foto ruim | S7: Executar na reforma
A8: Lâmpadas LED warm white (quarto e sala) e cool white (cozinha e banheiro | B8: Compra | C8: Estrutural | D8: 4 | E8: LED branco 18W Warm white, e cool white 110V/220V | F8: Barato | G8: 26.3 | H8: =D8*G8 | I8: Sim | J8: 126.72 | K8: https://pt.aliexpress.com/item/1005003294765840.html?spm=a2g0o.order_detail.order_detail_item.4.368d715cac8CXF&gatewayAdapt=glo2bra | L8: Luz boa = foto boa | M8: Comprado ✅ | N8: Já comprado | O8: Bloqueador | P8: — | Q8: Talita | R8: — | S8: Instalar
A9: Kit banheiro completo cromado 4 peças + ducha higiênica + acabamento de registro | B9: Compra | C9: Estrutural | D9: 1 | F9: Barato | G9: 26.3 | H9: =D9*G9 | I9: Sim | J9: 76.76 | K9: https://shopee.com.br/Kit-Banheiro-Completo-Cromado-Luxo-4-Pe%C3%A7as-Ducha-Higi%C3%AAnica-Alta-Press%C3%A3o-Chuveirinho-Acabamento-De-Registro-Luxo-i.843273344.58207705332 | L9: Luz boa = foto boa | M9: Comprado ✅ | N9: Já comprado | O9: Bloqueador | P9: — | Q9: Prestador | R9: — | S9: Instalar
A10: Jogo de lençol casal branco 4 peças | B10: Compra | C10: Quarto | D10: 2 | E10: 400 fios micropercal | F10: Interm. | G10: 110 | H10: =D10*G10 | I10: Sim | J10: 127.64 | K10: https://shopee.com.br/Jogo-de-Len%C3%A7ol-4-Pe%C3%A7as-400-Fios-Micropercal-Cama-Solteiro-Casal-Queen-e-King-i.805674361.23993804201 | L10: Regra dos 3 jogos | M10: Comprado ✅ (2 jogos) | N10: Já comprado | O10: Bloqueador | P10: — | Q10: Talita | R10: 2 jogos = mínimo p/ abrir; 3º dá folga | S10: Comprar 3º jogo pós-go-live
A11: Protetor de colchão impermeável | B11: Compra | C11: Quarto | D11: 2 | E11: Aba elástica, impermeável real, silencioso | F11: Melhor | G11: 100 | H11: =D11*G11 | I11: Pretendido | K11: Amazon | L11: Protege o ativo mais caro (comprar em breve) | M11: Pendente | N11: Comprar agora | O11: Bloqueador | P11: até 08/07 | Q11: Gestor | R11: Mancha no colchão + higiene (saúde e nota) | S11: COMPRAR JÁ — não receber hóspede sem
A12: Travesseiro antialérgico | B12: Compra | C12: Quarto | D12: 4 | E12: Firmeza média | F12: Interm. | G12: 55 | H12: =D12*G12 | I12: Sim | J12: 58.76 | K12: https://shopee.com.br/Kit-2-Travesseiros-50x70cm-Alto-e-Firme-Antial%C3%A9rgico-Lav%C3%A1vel-Conforto-Premium-Macio-i.688215758.23499414421 | L12: Trocar ~12 meses | M12: Comprado ✅ | N12: Já comprado | O12: Bloqueador | P12: — | Q12: — | R12: — | S12: —
A13: Protetor de travesseiro impermeável | B13: Compra | C13: Quarto | D13: 4 | E13: Com zíper | F13: Interm. | G13: 25 | H13: =D13*G13 | I13: Pretendido | K13: ML | L13: Comprar em breve | M13: Pendente | N13: Comprar agora | O13: Pré-go-live | P13: até 08/07 | Q13: Gestor | R13: Higiene do travesseiro reutilizado | S13: Comprar junto do protetor de colchão
A14: Edredom/colcha branca casal | B14: Compra | C14: Quarto | D14: 2 | E14: Lavável, leve | F14: Interm. | G14: 175 | H14: =D14*G14 | I14: Não | K14: ML | M14: Pendente | N14: Reconsiderar | O14: Pré-go-live | P14: até 09/07 | Q14: Gestor | R14: Cama 'pelada' na foto + frio de julho | S14: Comprar ao menos 1 cobre-leito/colcha
A15: Cobertor casal microfibra | B15: Compra | C15: Quarto | D15: 1 | E15: Para o inverno de BSB | F15: Barato | G15: 85 | H15: =D15*G15 | I15: Pretendido | K15: ML | L15: Utilizar a que já tem e comprar mais uma | M15: Pendente | N15: Comprar agora | O15: Bloqueador | P15: até 08/07 | Q15: Gestor | R15: Julho é frio em BSB: hóspede com frio = nota baixa | S15: Comprar já
A16: Toalha de banho branca | B16: Compra | C16: Banho | D16: 4 | E16: Algodão 400+ g/m² | F16: Interm. | G16: 50 | H16: =D16*G16 | I16: sim | J16: 79.45 | L16: Review pediu toalha | M16: Comprado ✅ | N16: Já comprado | O16: Bloqueador | P16: — | Q16: — | R16: — | S16: —
A17: Toalha de rosto branca | B17: Compra | C17: Banho | D17: 4 | E17: Algodão | F17: Barato | G17: 21 | H17: =D17*G17 | I17: Sim | J17: 39.19 | M17: Comprado ✅ | N17: Já comprado | O17: Bloqueador | P17: — | Q17: — | R17: — | S17: —
A18: Tapete de banheiro antiderrapante | B18: Compra | C18: Banho | D18: 2 | E18: - | F18: Barato | G18: 35 | H18: =D18*G18 | I18: Sim | J18: 30.72 | K18: https://shopee.com.br/Tapete-Antiderrapante-De-Banheiro-Super-Absorvente-Secagem-R%C3%A1pida-Chuveiro-Cozinha-Varanda-i.502621376.23393106789 | M18: Comprado ✅ | N18: Já comprado | O18: Bloqueador | P18: — | Q18: — | R18: — | S18: —
A19: Jogo de panelas 8pç (5 panelas + espatula, escumadeira e colher grande) | B19: Compra | C19: Cozinha | D19: 1 | E19: Antiaderente | F19: Melhor | G19: 275 | H19: =D19*G19 | I19: Sim | J19: 118.15 | K19: https://shopee.com.br/Jogo-de-panelas-com-8-pe%C3%A7as-Antiaderente-Preto-ou-Cereja-i.1790856718.58208225918 | M19: Comprado ✅ | N19: Já comprado | O19: Bloqueador | P19: — | Q19: — | R19: Confirmar se o set já inclui frigideira | S19: —
A20: Frigideira antiaderente | B20: Compra | C20: Cozinha | D20: 1 | E20: - | F20: Interm. | G20: 105 | H20: =D20*G20 | I20: Não | K20: ML | L20: Já tem no jogo de panela | M20: Pendente | N20: Avaliar | O20: Pré-go-live | P20: até 08/07 | Q20: Gestor | R20: Review pediu frigideira; dispensar só se o set já tem | S20: Confirmar set; senão comprar 1 barata
A21: Aparelho de jantar 20pç branco | B21: Compra | C21: Cozinha | D21: 1 | E21: Resistente, empilhável | F21: Interm. | G21: 295 | H21: =D21*G21 | I21: Sim | J21: 76.27 | K21: https://shopee.com.br/Aparelho-de-jantar-10-pe%C3%A7as-em-cer%C3%A2mica.-Prato-raso-fundo-sobremesa-pires-e-xicaras-i.349241462.20799000439?xptdk=14628c64-08ac-45e8-b163-8142f0f6ce58 | M21: Comprado ✅ | N21: Já comprado | O21: Bloqueador | P21: — | Q21: — | R21: — | S21: —
A22: Talheres 24pç | B22: Compra | C22: Cozinha | D22: 1 | E22: Preto | I22: Sim | J22: 28.86 | K22: https://shopee.com.br/Jogo-de-24-Talheres-Inox-Com-Brinde-Suporte-Gaveteiro-ou-Pote-Talher-Colher-Garfo-Premium-i.1482870808.22594635865 | M22: Comprado ✅ | N22: Já comprado | O22: Bloqueador | P22: — | Q22: — | R22: — | S22: —
A23: Copos | B23: Compra | C23: Cozinha | D23: 1 | E23: Faqueiro, copos, concha, espátula, coador | F23: Interm. | G23: 250 | H23: =D23*G23 | I23: Pretendido | K23: ML | L23: Utensilhos já tem, Pretende-se comprar apenas copos | M23: Pendente | N23: Comprar agora | O23: Bloqueador | P23: até 08/07 | Q23: Gestor | R23: Hóspede sem copo = função básica faltando | S23: Comprar já (barato)
A24: Cafeteira elétrica 220V | B24: Compra | C24: Cozinha | D24: 1 | E24: 600ml, filtro permanente | F24: Interm. | G24: 140 | H24: =D24*G24 | I24: Pretendido | K24: Amazon | L24: 220V! Brasília | M24: Pendente | N24: Comprar agora | O24: Pré-go-live | P24: até 09/07 | Q24: Gestor | R24: Café é alto ROI em avaliação; perde hospitalidade | S24: Comprar (barato)
A25: Detector de monoxido de carbono | B25: Compra | C25: Segurança | D25: 1 | I25: Sim | J25: 54.45 | K25: https://shopee.com.br/Detector-Digital-De-Mon%C3%B3xido-De-Carbono-LCD-Dom%C3%A9stico-CO-Alarme-Sensor-Monitor-i.191710221.40030381248 | M25: Comprado ✅ | N25: Já comprado | O25: Bloqueador | P25: — | Q25: — | R25: Segurança | S25: Instalar
A26: Detector de fumaça | B26: Compra | C26: Segurança | D26: 1 | E26: Bateria longa | F26: Interm. | G26: 105 | H26: =D26*G26 | I26: Sim | J26: 20.16 | K26: https://pt.aliexpress.com/item/1005003294765840.html?spm=a2g0o.order_detail.order_detail_item.4.368d715cac8CXF&gatewayAdapt=glo2bra | L26: Comodidade de segurança | M26: Comprado ✅ | N26: Já comprado | O26: Bloqueador | P26: — | Q26: — | R26: Segurança | S26: Instalar
A27: Extintor ABC | B27: Compra | C27: Segurança | D27: 1 | E27: Residencial | F27: Interm. | G27: 115 | H27: =D27*G27 | I27: Não | K27: ML | M27: Pendente | N27: Reconsiderar | O27: Pré-go-live | P27: até 09/07 | Q27: Gestor | R27: Segurança/confiança; baixo custo | S27: Reconsiderar comprar
A28: Kit primeiros socorros | B28: Compra | C28: Segurança | D28: 1 | E28: - | F28: Barato | G28: 65 | H28: =D28*G28 | I28: Não | K28: ML | M28: Pendente | N28: Reconsiderar | O28: Pré-go-live | P28: até 09/07 | Q28: Gestor | R28: Segurança/hospitalidade; item barato | S28: Opcional, recomendado
A29: Kit de limpeza inicial | B29: Compra | C29: Limpeza | D29: 1 | E29: Detergente, multiuso, panos, vassoura, rodo, balde | F29: Barato | G29: 185 | H29: =D29*G29 | I29: Pretendido | K29: ML | M29: Pendente | N29: Comprar agora | O29: Bloqueador | P29: até 09/07 | Q29: Gestor/Talita | R29: Sem material a secretária não faz o turnover | S29: Comprar antes da faxina
A30: Ventilador coluna/torre 220V | B30: Compra | C30: Conforto | D30: 1 | E30: Silencioso | F30: Interm. | G30: 225 | H30: =D30*G30 | I30: Pretendido | K30: ML | L30: AGORA (split fica p/ ago/set) | M30: Pendente | N30: Adiar | O30: Pós-go-live 30d | P30: até 31/08 | Q30: Gestor | R30: Conforto no calor (set+), NÃO em julho (frio) | S30: Comprar antes da estação quente
A31: Smart TV 32" Full HD | B31: Compra | C31: Conforto | D31: 1 | E31: Smart, Full HD | F31: Interm. | G31: 900 | H31: =D31*G31 | I31: Não | K31: ML | L31: TCL S5400A bom custo | M31: Pendente | N31: Não comprar agora | O31: Pós-ROI 60d | P31: após validar ROI | Q31: Gestor | R31: Lacuna de review/filtro de busca | S31: Reavaliar após 1ªs receitas
A32: Suporte de parede p/ TV | B32: Compra | C32: Conforto | D32: 1 | E32: Fixo | F32: Barato | G32: 55 | H32: =D32*G32 | I32: Não | K32: ML | M32: Pendente | N32: Não comprar agora | O32: Pós-ROI 60d | P32: com a TV | Q32: Gestor | R32: — | S32: Comprar junto da TV
A33: Armário/gaveteiro com chave | B33: Compra | C33: Automação | D33: 1 | E33: Para enxoval e estoque | F33: Interm. | G33: 400 | H33: =D33*G33 | I33: Não | K33: ML | L33: Será colocada apenas uma tranca em armário já existente | M33: Pendente | N33: Adiar | O33: Pós-go-live 30d | P33: até 31/07 | Q33: Gestor/Talita | R33: Segurança do estoque/enxoval | S33: Usar armário existente c/ cadeado por ora
A34: Organizadores + etiquetas | B34: Compra | C34: Automação | D34: 1 | E34: Caixas, cestos, etiquetas | F34: Barato | G34: 140 | H34: =D34*G34 | I34: Não | K34: ML | M34: Pendente | N34: Adiar | O34: Pós-go-live 30d | P34: até 31/07 | Q34: Talita | R34: Organização do estoque | S34: Depois
A35: Cofre de chave (lockbox) backup | B35: Compra | C35: Automação | D35: 1 | E35: Senha mecânica | F35: Interm. | G35: 105 | H35: =D35*G35 | I35: Não | K35: ML | L35: Backup da fechadura | M35: Pendente | N35: Reconsiderar | O35: Pré-go-live | P35: até 09/07 | Q35: Gestor | R35: Se a fechadura falhar, sem plano B de acesso remoto | S35: Reconsiderar (baixo custo, de-risca acesso)
A36: Estoque inicial de consumíveis | B36: Compra | C36: Reposição | D36: 1 | E36: Papel, sabonete, shampoo, café, açúcar, etc. (2 turnovers) | F36: Barato | G36: 225 | H36: =D36*G36 | I36: Pretendido | L36: Mercado local | M36: Pendente | N36: Comprar agora | O36: Bloqueador | P36: 09/07 | Q36: Gestor/Talita | R36: Hóspede sem itens básicos no check-in | S36: Comprar antes da 1ª reserva
A37: Fechadura eletrônica | B37: Compra | C37: Automação | D37: 1 | E37: Senha por hóspede | F37: Melhor | G37: 0 | H37: =D37*G37 | I37: Sim | J37: 400.35 | L37: JÁ COMPRADA ✅ | M37: Comprado ✅ | N37: Já comprado | O37: Bloqueador | P37: — | Q37: — | R37: Acesso remoto | S37: Testar gerar/expirar senha
A38: TOTAL | H38: =SUM(H4:H37) | J38: =SUM(J4:J37)

Sheet 2. Alta prioridade
A1: 2. ALTA PRIORIDADE
A2: Alto impacto com baixo custo. Logo após o essencial.
A3: Item | B3: Tipo | C3: Categoria | D3: Qtd | E3: Especificação mínima | F3: Qualidade | G3: Preço unit. estimado | H3: Total estimado | I3: Sua marcação (Sim/Pretend./Não) | J3: Valor real pago R$ | K3: Link | L3: Observação | M3: Status de execução | N3: Decisão CAPEX | O3: Classe go-live | P3: Data limite | Q3: Responsável | R3: Risco se adiar | S3: Próxima ação
A4: Cortina blackout neutra | B4: Compra | C4: Sala/Quarto | D4: 2 | E4: Corta-luz, tecido grosso | F4: Interm. | G4: 130 | H4: =D4*G4 | I4: Não | K4: ML | L4: Persiana já está suficiente vou aguardar as sujestões dos proximos hóspedes. Posso solicitar opinião quanto a isso de forma proativa | M4: Pendente | N4: Avaliar | O4: Pós-go-live 30d (condic.) | P4: até 31/07 | Q4: Gestor | R4: Sono ruim = nota; depende de já haver persiana | S4: Confirmar escurecimento atual; senão vira pré-go-live
A5: Decor / styling | B5: Compra | C5: Decoração | D5: 1 | E5: Quadros, plantas, itens p/ prateleiras vazias | F5: Barato | G5: 450 | H5: =D5*G5 | I5: Pretendido | K5: ML | L5: Foto de capa | M5: Pendente | N5: Comprar agora | O5: Pré-go-live | P5: até 09/07 | Q5: Gestor/Talita | R5: Foto de capa fraca = menos cliques | S5: Styling leve antes das fotos
A6: Espelho de corpo inteiro | B6: Compra | C6: Decoração | D6: 1 | E6: - | F6: Barato | G6: 225 | H6: =D6*G6 | I6: Sim | J6: 0 | L6: Já tinha | M6: Comprado ✅ | N6: Já comprado | O6: Pré-go-live | P6: — | Q6: — | R6: — | S6: —
A7: Tapete de sala | B7: Compra | C7: Sala | D7: 1 | E7: - | F7: Barato | G7: 165 | H7: =D7*G7 | I7: Não | K7: ML | L7: Aconchego | M7: Pendente | N7: Não comprar agora | O7: Pós-ROI 60d | P7: após ROI | Q7: Gestor | R7: Estético | S7: Depois
A8: Kit boas-vindas (recorrente) | B8: Compra | C8: Hospitalidade | D8: 1 | E8: Água, café, bilhete | F8: Barato | G8: 75 | H8: =D8*G8 | I8: Pretendido | L8: Vira avaliação 5★ | M8: Pendente | N8: Comprar agora | O8: Pré-go-live | P8: 1ª reserva | Q8: Gestor/Talita | R8: Perde 5★ fácil nos 1ºs hóspedes | S8: Ter para os primeiros hóspedes
A9: TOTAL | H9: =SUM(H4:H8) | J9: =SUM(J4:J8)

Sheet 3. Média prioridade
A1: 3. MÉDIA PRIORIDADE
A2: Conforto e durabilidade. Pode entrar nas primeiras semanas.
A3: Item | B3: Tipo | C3: Categoria | D3: Qtd | E3: Especificação mínima | F3: Qualidade | G3: Preço unit. estimado | H3: Total estimado | I3: Comprado/ Executado? | J3: Valor real pago R$ | K3: Link | L3: Observação
A4: Cadeira de trabalho | B4: Compra | C4: Sala/Trabalho | D4: 1 | E4: Confortável p/ home office | F4: Interm. | G4: 300 | H4: =D4*G4 | K4: ML | L4: Hóspede longo
A5: Capa de sofá / repaginar sofá | B5: Compra | C5: Sala | D5: 1 | E5: Cobrir desgaste do sofá bege | F5: Barato | G5: 190 | H5: =D5*G5 | K5: ML | L5: Conforto + foto
A6: Cuba/torneira nova (se datada) | B6: Compra | C6: Banho/Cozinha | D6: 1 | E6: Modelo simples | F6: Interm. | G6: 325 | H6: =D6*G6 | L6: Avaliar necessidade
A7: Pequenos reparos de móveis | B7: Serviço | C7: Estrutural | D7: 1 | E7: Puxadores, dobradiças, niveladores | F7: - | G7: 175 | H7: =D7*G7 | L7: Evita cara de usado
A8: TOTAL | H8: =SUM(H4:H7) | J8: =SUM(J4:J7)

Sheet 4. Diferenciação (2ª etapa)
A1: 4. DIFERENCIAÇÃO (2ª ETAPA)
A2: Sobe diária e nota. Pago com o caixa dos primeiros meses (split: ago/set).
A3: Item | B3: Tipo | C3: Categoria | D3: Qtd | E3: Especificação mínima | F3: Qualidade | G3: Preço unit. estimado | H3: Total estimado | I3: Comprado/ Executado? | J3: Valor real pago R$ | K3: Link | L3: Observação
A4: Ar-condicionado split 9000 BTUs inverter + instalação | B4: Compra | C4: Conforto | D4: 1 | E4: Inverter, frio, marca confiável (LG/Midea/Electrolux) | F4: Melhor | G4: 2500 | H4: =D4*G4 | K4: ML | L4: AGENDAR ago/set (antes do calor); pago com caixa
A5: Enxoval/decor extra (padrão hotel) | B5: Compra | C5: Quarto | D5: 1 | E5: Jogos a mais, mantas | F5: Interm. | G5: 350 | H5: =D5*G5 | L5: Percepção premium
A6: TOTAL | H6: =SUM(H4:H5) | J6: =SUM(J4:J5)

Sheet 5. Pode esperar
A1: 5. PODE ESPERAR
A2: Registro do que NÃO priorizar agora (e por quê).
A3: Item | B3: Tipo | C3: Categoria | D3: Qtd | E3: Especificação mínima | F3: Qualidade | G3: Preço unit. estimado | H3: Total estimado | I3: Comprado/ Executado? | J3: Valor real pago R$ | K3: Link | L3: Observação
A4: Troca de piso | B4: Serviço | C4: Estrutural | D4: 1 | E4: Só se realmente ruim | F4: - | G4: 0 | H4: =D4*G4 | L4: ROI baixo agora — NÃO VALE
A5: Máquina de lavar própria | B5: Compra | C5: Lavanderia | D5: 1 | E5: - | F5: - | G5: 0 | H5: =D5*G5 | L5: Condomínio tem lavanderia — NÃO priorizar
A6: Móveis grandes novos | B6: Compra | C6: Mobília | D6: 1 | E6: - | F6: - | G6: 0 | H6: =D6*G6 | L6: PODE ESPERAR (após 1ªs receitas)
A7: Bancada de pedra / reforma pesada | B7: Serviço | C7: Estrutural | D7: 1 | E7: - | F7: - | G7: 0 | H7: =D7*G7 | L7: NÃO VALE AGORA
A8: TOTAL | H8: =SUM(H4:H7) | J8: =SUM(J4:J7)
