Workbook

Sheet Instruções
B1: CONTROLE FISCAL E FINANCEIRO — AIRBNB 912 NORTE
B3: Para que serve esta planilha
B4: Registrar mês a mês a receita e os custos do apartamento e calcular AUTOMATICAMENTE:
B5: • o resultado líquido do imóvel e quanto vai para o Fundo de Aquisição (50%);
B6: • o Imposto de Renda mensal (carnê-leão) — já considerando a isenção até R$ 5.000/mês de 2026;
B7: • o resumo anual e se você fica obrigado a declarar.
B9: Como usar (rotina mensal de 5 minutos)
B10: 1. Vá na aba 'Lançamentos Mensais'.
B11: 2. Preencha SOMENTE as células AMARELAS do mês (receita e custos). As cinzas se calculam sozinhas.
B12: 3. Pegue os números no app do Airbnb (payout do mês) e nos boletos (condomínio, IPTU, luz, internet).
B13: 4. Em 'Outros rendimentos tributáveis' coloque salário/pró-labore/outras rendas do mês, se houver.
B14: 5. A coluna 'IR a pagar (DARF)' mostra o imposto do mês. Se der R$ 0, não há DARF a pagar naquele mês.
... B25: As regras de obrigatoriedade de declarar mudam todo ano — confirme o limite na aba 'Resumo Anual'.

Sheet Tabela IR
A1: TABELA PROGRESSIVA MENSAL — IRPF 2026 (editável)
A3: Faixa (base de cálculo mensal) | B3: Limite superior (R$) | C3: Alíquota | D3: Parcela a deduzir (R$)
A4: Até 2.259,20 | B4: 2259.2 | C4: 0 | D4: 0
A5: De 2.259,21 a 2.826,65 | B5: 2826.65 | C5: 0.075 | D5: 169.44
A6: De 2.826,66 a 3.751,05 | B6: 3751.05 | C6: 0.15 | D6: 381.44
A7: De 3.751,06 a 4.664,68 | B7: 4664.68 | C7: 0.225 | D7: 662.77
A8: Acima de 4.664,68 | B8: 99999999 | C8: 0.275 | D8: 896
A10: PARÂMETROS 2026 (Lei 15.270/2025)
A11: Isenção total até (R$/mês) — zera o IR | B11: 5000
A12: Teto da redução parcial (R$/mês) | B12: 7350
A13: Desconto simplificado mensal (opção, p/ serviços) (R$) | B13: 564.8
A15: Obs.: a faixa R$ 5.000–7.350 tem redução parcial não detalhada aqui (sua renda fica abaixo).
A16: Se um mês passar de R$ 5.000 de base tributável, me avise para incluir a fórmula da redução parcial.

Sheet Lançamentos Mensais
A1: LANÇAMENTOS MENSAIS — preencha as colunas AMARELAS
A2: Amarelo = você preenche | Cinza = calculado | Verde = resultado
A3: Mês | B3: Receita hospedagem (diárias) R$ | C3: Taxa de limpeza recebida R$ | D3: Taxa Airbnb paga R$ | E3: Condomínio R$ | F3: IPTU do mês R$ | G3: Manutenção dedutível R$ | H3: Outros custos (luz/net/diarista/etc) R$ | I3: Outros rendim. tributáveis R$ | J3: Receita total R$ | K3: Deduções fiscais R$ | L3: Base tributável aluguel R$ | M3: Total tributável mês R$ | N3: Imposto pela tabela R$ | O3: IR a pagar (DARF) R$ | P3: Líquido do imóvel R$ | Q3: 50% Fundo Aquisição R$
A4: Janeiro | E4: 380 | F4: 90 | H4: 190 | J4: =B4+C4 | K4: =D4+E4+F4+G4 | L4: =MAX(0,J4-K4) | M4: =L4+I4 | N4: =IF(M4<='Tabela IR'!$B$4,0,IF(M4<='Tabela IR'!$B$5,M4*'Tabela IR'!$C$5-'Tabela IR'!$D$5,IF(M4<='Tabela IR'!$B$6,M4*'Tabela IR'!$C$6-'Tabela IR'!$D$6,IF(M4<='Tabela IR'!$B$7,M4*'Tabela IR'!$C$7-'Tabela IR'!$D$7,M4*'Tabela IR'!$C$8-'Tabela IR'!$D$8)))) | O4: =IF(M4<='Tabela IR'!$B$11,0,N4) | P4: =J4-D4-E4-F4-G4-H4-O4 | Q4: =P4*0.5
A5: Fevereiro | E5: 380 | F5: 90 | H5: 190 | J5: =B5+C5 | K5: =D5+E5+F5+G5 | L5: =MAX(0,J5-K5) | M5: =L5+I5 | N5: =IF(M5<='Tabela IR'!$B$4,0,IF(M5<='Tabela IR'!$B$5,M5*'Tabela IR'!$C$5-'Tabela IR'!$D$5,IF(M5<='Tabela IR'!$B$6,M5*'Tabela IR'!$C$6-'Tabela IR'!$D$6,IF(M5<='Tabela IR'!$B$7,M5*'Tabela IR'!$C$7-'Tabela IR'!$D$7,M5*'Tabela IR'!$C$8-'Tabela IR'!$D$8)))) | O5: =IF(M5<='Tabela IR'!$B$11,0,N5) | P5: =J5-D5-E5-F5-G5-H5-O5 | Q5: =P5*0.5
A6: Março | E6: 380 | F6: 90 | H6: 190 | J6: =B6+C6 | K6: =D6+E6+F6+G6 | L6: =MAX(0,J6-K6) | M6: =L6+I6 | N6: =IF(M6<='Tabela IR'!$B$4,0,IF(M6<='Tabela IR'!$B$5,M6*'Tabela IR'!$C$5-'Tabela IR'!$D$5,IF(M6<='Tabela IR'!$B$6,M6*'Tabela IR'!$C$6-'Tabela IR'!$D$6,IF(M6<='Tabela IR'!$B$7,M6*'Tabela IR'!$C$7-'Tabela IR'!$D$7,M6*'Tabela IR'!$C$8-'Tabela IR'!$D$8)))) | O6: =IF(M6<='Tabela IR'!$B$11,0,N6) | P6: =J6-D6-E6-F6-G6-H6-O6 | Q6: =P6*0.5
A7: Abril | E7: 380 | F7: 90 | H7: 190 | J7: =B7+C7 | K7: =D7+E7+F7+G7 | L7: =MAX(0,J7-K7) | M7: =L7+I7 | N7: =IF(M7<='Tabela IR'!$B$4,0,IF(M7<='Tabela IR'!$B$5,M7*'Tabela IR'!$C$5-'Tabela IR'!$D$5,IF(M7<='Tabela IR'!$B$6,M7*'Tabela IR'!$C$6-'Tabela IR'!$D$6,IF(M7<='Tabela IR'!$B$7,M7*'Tabela IR'!$C$7-'Tabela IR'!$D$7,M7*'Tabela IR'!$C$8-'Tabela IR'!$D$8)))) | O7: =IF(M7<='Tabela IR'!$B$11,0,N7) | P7: =J7-D7-E7-F7-G7-H7-O7 | Q7: =P7*0.5
A8: Maio | E8: 380 | F8: 90 | H8: 190 | J8: =B8+C8 | K8: =D8+E8+F8+G8 | L8: =MAX(0,J8-K8) | M8: =L8+I8 | N8: =IF(M8<='Tabela IR'!$B$4,0,IF(M8<='Tabela IR'!$B$5,M8*'Tabela IR'!$C$5-'Tabela IR'!$D$5,IF(M8<='Tabela IR'!$B$6,M8*'Tabela IR'!$C$6-'Tabela IR'!$D$6,IF(M8<='Tabela IR'!$B$7,M8*'Tabela IR'!$C$7-'Tabela IR'!$D$7,M8*'Tabela IR'!$C$8-'Tabela IR'!$D$8)))) | O8: =IF(M8<='Tabela IR'!$B$11,0,N8) | P8: =J8-D8-E8-F8-G8-H8-O8 | Q8: =P8*0.5
A9: Junho | E9: 380 | F9: 90 | H9: 190 | J9: =B9+C9 | K9: =D9+E9+F9+G9 | L9: =MAX(0,J9-K9) | M9: =L9+I9 | N9: =IF(M9<='Tabela IR'!$B$4,0,IF(M9<='Tabela IR'!$B$5,M9*'Tabela IR'!$C$5-'Tabela IR'!$D$5,IF(M9<='Tabela IR'!$B$6,M9*'Tabela IR'!$C$6-'Tabela IR'!$D$6,IF(M9<='Tabela IR'!$B$7,M9*'Tabela IR'!$C$7-'Tabela IR'!$D$7,M9*'Tabela IR'!$C$8-'Tabela IR'!$D$8)))) | O9: =IF(M9<='Tabela IR'!$B$11,0,N9) | P9: =J9-D9-E9-F9-G9-H9-O9 | Q9: =P9*0.5
A10: Julho | E10: 380 | F10: 90 | H10: 190 | J10: =B10+C10 | K10: =D10+E10+F10+G10 | L10: =MAX(0,J10-K10) | M10: =L10+I10 | N10: =IF(M10<='Tabela IR'!$B$4,0,IF(M10<='Tabela IR'!$B$5,M10*'Tabela IR'!$C$5-'Tabela IR'!$D$5,IF(M10<='Tabela IR'!$B$6,M10*'Tabela IR'!$C$6-'Tabela IR'!$D$6,IF(M10<='Tabela IR'!$B$7,M10*'Tabela IR'!$C$7-'Tabela IR'!$D$7,M10*'Tabela IR'!$C$8-'Tabela IR'!$D$8)))) | O10: =IF(M10<='Tabela IR'!$B$11,0,N10) | P10: =J10-D10-E10-F10-G10-H10-O10 | Q10: =P10*0.5
A11: Agosto | E11: 380 | F11: 90 | H11: 190 | J11: =B11+C11 | K11: =D11+E11+F11+G11 | L11: =MAX(0,J11-K11) | M11: =L11+I11 | N11: =IF(M11<='Tabela IR'!$B$4,0,IF(M11<='Tabela IR'!$B$5,M11*'Tabela IR'!$C$5-'Tabela IR'!$D$5,IF(M11<='Tabela IR'!$B$6,M11*'Tabela IR'!$C$6-'Tabela IR'!$D$6,IF(M11<='Tabela IR'!$B$7,M11*'Tabela IR'!$C$7-'Tabela IR'!$D$7,M11*'Tabela IR'!$C$8-'Tabela IR'!$D$8)))) | O11: =IF(M11<='Tabela IR'!$B$11,0,N11) | P11: =J11-D11-E11-F11-G11-H11-O11 | Q11: =P11*0.5
A12: Setembro | E12: 380 | F12: 90 | H12: 190 | J12: =B12+C12 | K12: =D12+E12+F12+G12 | L12: =MAX(0,J12-K12) | M12: =L12+I12 | N12: =IF(M12<='Tabela IR'!$B$4,0,IF(M12<='Tabela IR'!$B$5,M12*'Tabela IR'!$C$5-'Tabela IR'!$D$5,IF(M12<='Tabela IR'!$B$6,M12*'Tabela IR'!$C$6-'Tabela IR'!$D$6,IF(M12<='Tabela IR'!$B$7,M12*'Tabela IR'!$C$7-'Tabela IR'!$D$7,M12*'Tabela IR'!$C$8-'Tabela IR'!$D$8)))) | O12: =IF(M12<='Tabela IR'!$B$11,0,N12) | P12: =J12-D12-E12-F12-G12-H12-O12 | Q12: =P12*0.5
A13: Outubro | E13: 380 | F13: 90 | H13: 190 | J13: =B13+C13 | K13: =D13+E13+F13+G13 | L13: =MAX(0,J13-K13) | M13: =L13+I13 | N13: =IF(M13<='Tabela IR'!$B$4,0,IF(M13<='Tabela IR'!$B$5,M13*'Tabela IR'!$C$5-'Tabela IR'!$D$5,IF(M13<='Tabela IR'!$B$6,M13*'Tabela IR'!$C$6-'Tabela IR'!$D$6,IF(M13<='Tabela IR'!$B$7,M13*'Tabela IR'!$C$7-'Tabela IR'!$D$7,M13*'Tabela IR'!$C$8-'Tabela IR'!$D$8)))) | O13: =IF(M13<='Tabela IR'!$B$11,0,N13) | P13: =J13-D13-E13-F13-G13-H13-O13 | Q13: =P13*0.5
A14: Novembro | E14: 380 | F14: 90 | H14: 190 | J14: =B14+C14 | K14: =D14+E14+F14+G14 | L14: =MAX(0,J14-K14) | M14: =L14+I14 | N14: =IF(M14<='Tabela IR'!$B$4,0,IF(M14<='Tabela IR'!$B$5,M14*'Tabela IR'!$C$5-'Tabela IR'!$D$5,IF(M14<='Tabela IR'!$B$6,M14*'Tabela IR'!$C$6-'Tabela IR'!$D$6,IF(M14<='Tabela IR'!$B$7,M14*'Tabela IR'!$C$7-'Tabela IR'!$D$7,M14*'Tabela IR'!$C$8-'Tabela IR'!$D$8)))) | O14: =IF(M14<='Tabela IR'!$B$11,0,N14) | P14: =J14-D14-E14-F14-G14-H14-O14 | Q14: =P14*0.5
A15: Dezembro | E15: 380 | F15: 90 | H15: 190 | J15: =B15+C15 | K15: =D15+E15+F15+G15 | L15: =MAX(0,J15-K15) | M15: =L15+I15 | N15: =IF(M15<='Tabela IR'!$B$4,0,IF(M15<='Tabela IR'!$B$5,M15*'Tabela IR'!$C$5-'Tabela IR'!$D$5,IF(M15<='Tabela IR'!$B$6,M15*'Tabela IR'!$C$6-'Tabela IR'!$D$6,IF(M15<='Tabela IR'!$B$7,M15*'Tabela IR'!$C$7-'Tabela IR'!$D$7,M15*'Tabela IR'!$C$8-'Tabela IR'!$D$8)))) | O15: =IF(M15<='Tabela IR'!$B$11,0,N15) | P15: =J15-D15-E15-F15-G15-H15-O15 | Q15: =P15*0.5
A16: TOTAL ANO | B16: =SUM(B4:B15) | C16: =SUM(C4:C15) | D16: =SUM(D4:D15) | E16: =SUM(E4:E15) | F16: =SUM(F4:F15) | G16: =SUM(G4:G15) | H16: =SUM(H4:H15) | I16: =SUM(I4:I15) | ... M16: =SUM(M4:M15) | O16: =SUM(O4:O15) | P16: =SUM(P4:P15) | Q16: =SUM(Q4:Q15)

Sheet Resumo Anual
A1: RESUMO ANUAL
A3: Receita total do ano (hospedagem + limpeza) | B3: ='Lançamentos Mensais'!J16
A4: Deduções fiscais do ano | B4: ='Lançamentos Mensais'!K16
A5: Base tributável de aluguel no ano | B5: ='Lançamentos Mensais'!L16
A6: Imposto de Renda pago no ano (carnê-leão) | B6: ='Lançamentos Mensais'!O16
A7: Outros custos operacionais (luz/net/diarista/etc.) | B7: ='Lançamentos Mensais'!H16
A8: Taxa Airbnb paga no ano | B8: ='Lançamentos Mensais'!D16
A9: LÍQUIDO do imóvel no ano | B9: ='Lançamentos Mensais'!P16
A10: Destinado ao Fundo de Aquisição (50%) | B10: ='Lançamentos Mensais'!Q16
A12: OBRIGATORIEDADE DE DECLARAR (IRPF anual)
A13: Limite de rendimentos tributáveis no ano (editável)* | B13: 33888
A14: Sua base tributável de aluguel no ano | B14: ='Lançamentos Mensais'!L16
A15: Recebeu aluguel sujeito a carnê-leão? | B15: =IF('Lançamentos Mensais'!L16>0,"SIM","NÃO")
A16: Precisa entregar a declaração anual? | B16: =IF(OR(B14>B13,'Lançamentos Mensais'!L16>0),"SIM — deve declarar","Verificar outros critérios")
A18: * Quem recebe rendimento de aluguel sujeito ao carnê-leão geralmente já fica
A19: obrigado a declarar, mesmo que o imposto a pagar seja R$ 0. Confirme o limite do ano.
